lily_env/__init__.py
lily_env/cli.py
lily_env/constants.py
lily_env/crypto.py
lily_env/env_validators.py
lily_env/exceptions.py
lily_env/fields.py
lily_env/fields_validators.py
lily_env/git.py
lily_env/parser.py
lily_env/utils.py
lily_env-1.0.0.data/data/README.md
lily_env-1.0.0.data/data/requirements.txt
tests/__init__.py
tests/test_cli.py
tests/test_crypto.py
tests/test_fields.py
tests/test_fields_validators.py
tests/test_git.py
tests/test_parser.py
tests/test_utils.py
lily_env-1.0.0.dist-info/METADATA
lily_env-1.0.0.dist-info/WHEEL
lily_env-1.0.0.dist-info/entry_points.txt
lily_env-1.0.0.dist-info/top_level.txt
lily_env-1.0.0.dist-info/RECORD
