Metadata-Version: 2.1
Name: lily-env
Version: 1.0.0
Summary: Lily extension for managing environment variables, their validity etc.
Home-page: https://github.com/cosphere-org/lily-env
Author: CoSphere Tech
Author-email: contact@cosphere.org
License: UNKNOWN
Keywords: lily,django,drf
Platform: UNKNOWN
Requires-Dist: validators (>=0.12.6)
Requires-Dist: Click (>=7.0)
Requires-Dist: PyYAML (>=3.13)
Requires-Dist: python-gnupg (==0.4.6)
Requires-Dist: bash (==0.6)
